password_secure_password_generator/__init__.py
password_secure_password_generator/idgenerator.py
password_secure_password_generator-0.1.0.dist-info/METADATA
password_secure_password_generator-0.1.0.dist-info/WHEEL
password_secure_password_generator-0.1.0.dist-info/top_level.txt
password_secure_password_generator-0.1.0.dist-info/RECORD
