Metadata-Version: 2.4
Name: password_secure_password_generator
Version: 0.1.0
Summary: To generate secure unique password.
Author-email: Aman <amanraj0001@gmail.com>
Classifier: Programming Language :: Python :: 3
Classifier: License :: OSI Approved :: MIT License
Classifier: Operating System :: OS Independent
Requires-Python: >=3.7
